freeselcall/.DS_Store
freeselcall/TODO
freeselcall/__init__.py
freeselcall/__main__.py
freeselcall/audio.py
freeselcall/chan_test_tune.py
freeselcall/fsk_build.py
freeselcall/modem.py
freeselcall/notes for decoding selcall
freeselcall/pagecall_magic.py
freeselcall/rigctl.py
freeselcall/shell.py
freeselcall/static/bootstrap-5.3.3-dist/.DS_Store
freeselcall/static/bootstrap-5.3.3-dist/css/bootstrap-grid.css
freeselcall/static/bootstrap-5.3.3-dist/css/bootstrap-grid.css.map
freeselcall/static/bootstrap-5.3.3-dist/css/bootstrap-grid.min.css
freeselcall/static/bootstrap-5.3.3-dist/css/bootstrap-grid.min.css.map
freeselcall/static/bootstrap-5.3.3-dist/css/bootstrap-grid.rtl.css
freeselcall/static/bootstrap-5.3.3-dist/css/bootstrap-grid.rtl.css.map
freeselcall/static/bootstrap-5.3.3-dist/css/bootstrap-grid.rtl.min.css
freeselcall/static/bootstrap-5.3.3-dist/css/bootstrap-grid.rtl.min.css.map
freeselcall/static/bootstrap-5.3.3-dist/css/bootstrap-reboot.css
freeselcall/static/bootstrap-5.3.3-dist/css/bootstrap-reboot.css.map
freeselcall/static/bootstrap-5.3.3-dist/css/bootstrap-reboot.min.css
freeselcall/static/bootstrap-5.3.3-dist/css/bootstrap-reboot.min.css.map
freeselcall/static/bootstrap-5.3.3-dist/css/bootstrap-reboot.rtl.css
freeselcall/static/bootstrap-5.3.3-dist/css/bootstrap-reboot.rtl.css.map
freeselcall/static/bootstrap-5.3.3-dist/css/bootstrap-reboot.rtl.min.css
freeselcall/static/bootstrap-5.3.3-dist/css/bootstrap-reboot.rtl.min.css.map
freeselcall/static/bootstrap-5.3.3-dist/css/bootstrap-utilities.css
freeselcall/static/bootstrap-5.3.3-dist/css/bootstrap-utilities.css.map
freeselcall/static/bootstrap-5.3.3-dist/css/bootstrap-utilities.min.css
freeselcall/static/bootstrap-5.3.3-dist/css/bootstrap-utilities.min.css.map
freeselcall/static/bootstrap-5.3.3-dist/css/bootstrap-utilities.rtl.css
freeselcall/static/bootstrap-5.3.3-dist/css/bootstrap-utilities.rtl.css.map
freeselcall/static/bootstrap-5.3.3-dist/css/bootstrap-utilities.rtl.min.css
freeselcall-0.0.7.dist-info/LICENSE
freeselcall-0.0.7.dist-info/METADATA
freeselcall-0.0.7.dist-info/WHEEL
freeselcall-0.0.7.dist-info/entry_points.txt
freeselcall-0.0.7.dist-info/RECORD
